logging_json/__init__.py
logging_json/_formatter.py
logging_json/py.typed
logging_json/version.py
logging_json-0.5.0.dist-info/LICENSE
logging_json-0.5.0.dist-info/METADATA
logging_json-0.5.0.dist-info/WHEEL
logging_json-0.5.0.dist-info/top_level.txt
logging_json-0.5.0.dist-info/RECORD
