Metadata-Version: 2.1
Name: logging_json
Version: 0.5.0
Summary: JSON formatter for python logging
Author-email: Colin Bounouar <colin.bounouar.dev@gmail.com>
Maintainer-email: Colin Bounouar <colin.bounouar.dev@gmail.com>
License: MIT License
Project-URL: documentation, https://colin-b.github.io/logging_json/
Project-URL: repository, https://github.com/Colin-b/logging_json
Project-URL: changelog, https://github.com/Colin-b/logging_json/blob/master/CHANGELOG.md
Project-URL: issues, https://github.com/Colin-b/logging_json/issues
Keywords: logging,json
Classifier: Development Status :: 5 - Production/Stable
Classifier: Intended Audience :: Developers
Classifier: License :: OSI Approved :: MIT License
Classifier: Natural Language :: English
Classifier: Typing :: Typed
Classifier: Programming Language :: Python
Classifier: Programming Language :: Python :: 3
Classifier: Programming Language :: Python :: 3.7
Classifier: Programming Language :: Python :: 3.8
Classifier: Programming Language :: Python :: 3.9
Classifier: Programming Language :: Python :: 3.10
Classifier: Programming Language :: Python :: 3.11
Classifier: Programming Language :: Python :: 3.12
Classifier: Topic :: Software Development :: Build Tools
Requires-Python: >=3.7
License-File: LICENSE
Provides-Extra: testing
Requires-Dist: time-machine ==2.* ; extra == 'testing'
Requires-Dist: pytest-cov ==4.* ; extra == 'testing'
